m3uify/__init__.py
m3uify/__main__.py
m3uify/app.py
m3uify-1.0.0.dist-info/METADATA
m3uify-1.0.0.dist-info/WHEEL
m3uify-1.0.0.dist-info/entry_points.txt
m3uify-1.0.0.dist-info/top_level.txt
m3uify-1.0.0.dist-info/RECORD
