Metadata-Version: 2.4
Name: m3uify
Version: 1.0.0
Summary: A terminal UI tool to browse Spotify playlists, create M3U files, and download songs using spotdl.
Author-email: Joshua Lander <your-email@example.com>
Requires-Python: >=3.9
Requires-Dist: spotipy>=2.23.0
Requires-Dist: spotdl>=4.2.0
